{
  "id": "04-etre-avoir",
  "title": "Les verbes être et avoir",
  "description": "The two most important French verbs. Present-tense conjugation + when to use each.",
  "estimated_minutes": 14,
  "cards": [
    {
      "id": "pron-je",
      "front": "je",
      "back": "I",
      "notes": "Elides to **j'** before a vowel: *j'ai*, *j'aime*, *j'écoute*.",
      "tags": [
        "pronoun",
        "subject"
      ]
    },
    {
      "id": "pron-tu",
      "front": "tu",
      "back": "you (informal singular)",
      "notes": "Used with friends, family, kids, peers. NEVER for a stranger or a customer — that's *vous*.",
      "tags": [
        "pronoun",
        "subject",
        "informal"
      ]
    },
    {
      "id": "pron-il",
      "front": "il",
      "back": "he / it (m.)",
      "notes": "Also used for masculine objects: *le livre — il est rouge* (the book — it is red).",
      "tags": [
        "pronoun",
        "subject"
      ]
    },
    {
      "id": "pron-elle",
      "front": "elle",
      "back": "she / it (f.)",
      "notes": "Also used for feminine objects: *la chaise — elle est verte*.",
      "tags": [
        "pronoun",
        "subject"
      ]
    },
    {
      "id": "pron-nous",
      "front": "nous",
      "back": "we",
      "notes": "In casual speech, often replaced by *on* (*on est* = we are). At A1, stick with *nous*.",
      "tags": [
        "pronoun",
        "subject"
      ]
    },
    {
      "id": "pron-vous",
      "front": "vous",
      "back": "you (formal or plural)",
      "notes": "Two uses: (1) formal singular (one stranger, one professor), (2) plural (multiple people, any formality). The verb form is the same.",
      "tags": [
        "pronoun",
        "subject",
        "formal"
      ]
    },
    {
      "id": "pron-ils",
      "front": "ils",
      "back": "they (m. or mixed)",
      "notes": "Used for groups of all men or mixed men+women. Even one man in a group of women makes the group *ils*.",
      "tags": [
        "pronoun",
        "subject",
        "plural"
      ]
    },
    {
      "id": "pron-elles",
      "front": "elles",
      "back": "they (f. — all women / all feminine)",
      "notes": "Only when every member of the group is feminine.",
      "tags": [
        "pronoun",
        "subject",
        "plural"
      ]
    },
    {
      "id": "etre-suis",
      "front": "je suis",
      "back": "I am",
      "tags": [
        "verb",
        "etre",
        "present"
      ]
    },
    {
      "id": "etre-es",
      "front": "tu es",
      "back": "you are (informal sg.)",
      "tags": [
        "verb",
        "etre",
        "present"
      ]
    },
    {
      "id": "etre-est",
      "front": "il/elle est",
      "back": "he/she/it is",
      "tags": [
        "verb",
        "etre",
        "present"
      ]
    },
    {
      "id": "etre-sommes",
      "front": "nous sommes",
      "back": "we are",
      "tags": [
        "verb",
        "etre",
        "present"
      ]
    },
    {
      "id": "etre-etes",
      "front": "vous êtes",
      "back": "you are (formal / pl.)",
      "notes": "Note the circumflex on the ê — it's a hint that an old s used to be there (compare English *est*).",
      "tags": [
        "verb",
        "etre",
        "present"
      ]
    },
    {
      "id": "etre-sont",
      "front": "ils/elles sont",
      "back": "they are",
      "tags": [
        "verb",
        "etre",
        "present"
      ]
    },
    {
      "id": "avoir-ai",
      "front": "j'ai",
      "back": "I have",
      "notes": "Elided: *je ai* never happens; always **j'ai**.",
      "tags": [
        "verb",
        "avoir",
        "present"
      ]
    },
    {
      "id": "avoir-as",
      "front": "tu as",
      "back": "you have (informal sg.)",
      "tags": [
        "verb",
        "avoir",
        "present"
      ]
    },
    {
      "id": "avoir-a",
      "front": "il/elle a",
      "back": "he/she/it has",
      "notes": "No accent. *il a* (he has) vs *il à* (which doesn't exist as a sentence — *à* is a preposition).",
      "tags": [
        "verb",
        "avoir",
        "present"
      ]
    },
    {
      "id": "avoir-avons",
      "front": "nous avons",
      "back": "we have",
      "tags": [
        "verb",
        "avoir",
        "present"
      ]
    },
    {
      "id": "avoir-avez",
      "front": "vous avez",
      "back": "you have (formal / pl.)",
      "tags": [
        "verb",
        "avoir",
        "present"
      ]
    },
    {
      "id": "avoir-ont",
      "front": "ils/elles ont",
      "back": "they have",
      "notes": "Don't confuse with *sont* (they are). One letter, totally different meaning.",
      "tags": [
        "verb",
        "avoir",
        "present"
      ]
    }
  ],
  "steps": [
    {
      "id": "intro",
      "type": "theory",
      "title": "The two most important verbs",
      "body": "# *Être* and *avoir*\n\nIf you only learn two French verbs at A1, learn **être** (to be) and **avoir** (to have). Together they cover:\n\n- Identity: *Je **suis** étudiant.* — I am a student.\n- Description: *Elle **est** grande.* — She is tall.\n- Possession: *J'**ai** un chat.* — I have a cat.\n- Age: *Tu **as** vingt ans.* — You are twenty (lit.: you have twenty years).\n- Plus the **passé composé** — French's main past tense — is built from *avoir* + past participle (Lesson 10).\n\nBoth verbs are **irregular** — the forms don't follow a pattern, you have to memorise them. Same in English (am / are / is / was / were), same in Spanish (soy / eres / es), same in German (bin / bist / ist). It's worth the upfront effort."
    },
    {
      "id": "step-etre",
      "type": "theory",
      "title": "Être — to be",
      "body": "## Present tense of *être*\n\n| Subject | Form |\n|---|---|\n| je | **suis** |\n| tu | **es** |\n| il / elle | **est** |\n| nous | **sommes** |\n| vous | **êtes** |\n| ils / elles | **sont** |\n\nPronunciation traps:\n- *suis* — silent **s** at the end, sounds like \"swee\"\n- *est* — the **s** and **t** are silent: just \"eh\"\n- *êtes* — the circumflex marks an old **s**: pronounced \"ett\"\n- *sont* — nasal vowel + silent **t**: \"sohn\"\n\nUse *être* for: identity, profession, nationality, description, location.\n\n*Je **suis** français. Tu **es** ici. Nous **sommes** prêts.*"
    },
    {
      "id": "ex-match-etre",
      "type": "exercise",
      "title": "Match être forms",
      "exercise": {
        "id": "ex-match-etre",
        "type": "matching",
        "prompt": "Match each subject pronoun with the correct form of *être*.",
        "card_ids": [
          "etre-suis",
          "etre-es",
          "etre-est",
          "etre-sommes",
          "etre-etes",
          "etre-sont"
        ],
        "pairs": [
          {
            "left": "je",
            "right": "suis"
          },
          {
            "left": "tu",
            "right": "es"
          },
          {
            "left": "il",
            "right": "est"
          },
          {
            "left": "nous",
            "right": "sommes"
          },
          {
            "left": "vous",
            "right": "êtes"
          },
          {
            "left": "ils",
            "right": "sont"
          }
        ],
        "direction": "target_to_source"
      }
    },
    {
      "id": "ex-free-etre-vous",
      "type": "exercise",
      "title": "Conjugate être — vous",
      "exercise": {
        "id": "ex-free-etre-vous",
        "type": "free_text",
        "prompt": "Type the form of *être* that goes with **vous**.",
        "card_ids": [
          "etre-etes"
        ],
        "accept": [
          "êtes",
          "Êtes",
          "etes"
        ],
        "hint": "Has a circumflex. Sounds like \"ett\".",
        "distractors": [
          "est",
          "sommes",
          "sont"
        ],
        "direction": "target_to_source"
      }
    },
    {
      "id": "step-avoir",
      "type": "theory",
      "title": "Avoir — to have",
      "body": "## Present tense of *avoir*\n\n| Subject | Form |\n|---|---|\n| je (j') | **ai** |\n| tu | **as** |\n| il / elle | **a** |\n| nous | **avons** |\n| vous | **avez** |\n| ils / elles | **ont** |\n\nMandatory elision: *je* + *ai* always becomes **j'ai**. You'll never see *je ai*.\n\nUse *avoir* for: possession, age, certain idioms.\n\n- *J'**ai** trois enfants.* — I have three children.\n- *Vous **avez** vingt ans.* — You are twenty years old. (Literally: you HAVE twenty years.)\n- *Ils **ont** faim.* — They are hungry. (Literally: they HAVE hunger.)\n\nFrench uses *avoir* where English uses *be* for age, hunger, thirst, fear, and being right or wrong. Translate by meaning, not word-for-word."
    },
    {
      "id": "ex-match-avoir",
      "type": "exercise",
      "title": "Match avoir forms",
      "exercise": {
        "id": "ex-match-avoir",
        "type": "matching",
        "prompt": "Match each subject pronoun with the correct form of *avoir*.",
        "card_ids": [
          "avoir-ai",
          "avoir-as",
          "avoir-a",
          "avoir-avons",
          "avoir-avez",
          "avoir-ont"
        ],
        "pairs": [
          {
            "left": "j'",
            "right": "ai"
          },
          {
            "left": "tu",
            "right": "as"
          },
          {
            "left": "elle",
            "right": "a"
          },
          {
            "left": "nous",
            "right": "avons"
          },
          {
            "left": "vous",
            "right": "avez"
          },
          {
            "left": "ils",
            "right": "ont"
          }
        ],
        "direction": "target_to_source"
      }
    },
    {
      "id": "ex-free-avoir-nous",
      "type": "exercise",
      "title": "Conjugate avoir — nous",
      "exercise": {
        "id": "ex-free-avoir-nous",
        "type": "free_text",
        "prompt": "Type the form of *avoir* that goes with **nous**.",
        "card_ids": [
          "avoir-avons"
        ],
        "accept": [
          "avons",
          "Avons",
          "AVONS"
        ],
        "hint": "Three syllables: a-vons.",
        "distractors": [
          "avez",
          "ont",
          "ai"
        ],
        "direction": "target_to_source"
      }
    },
    {
      "id": "step-vous-formal",
      "type": "theory",
      "title": "Tu or vous?",
      "body": "## The *tu* / *vous* choice\n\nFrench requires you to pick one of two forms for \"you\":\n\n| Situation | Use |\n|---|---|\n| Talking to one friend, family member, child | **tu** |\n| Talking to a stranger, customer, professor (one person) | **vous** |\n| Talking to more than one person, any formality | **vous** |\n\nNote that **vous** does double duty (formal singular AND any plural). The verb conjugation is the same — context tells you which one is meant.\n\nWhen in doubt with someone new, use **vous**. They'll let you know if it's OK to switch to **tu** (\"*on se tutoie*\" — let's use tu).\n\nAt A1, when you don't know which to pick, **vous** is the safer choice."
    },
    {
      "id": "ex-pick-vous",
      "type": "exercise",
      "title": "Pick tu or vous",
      "exercise": {
        "id": "ex-pick-vous",
        "type": "picture_choice",
        "prompt": "You are addressing your professor in class. Which pronoun do you use?",
        "card_ids": [
          "pron-tu",
          "pron-vous"
        ],
        "images": [
          {
            "src": "assets/img/teacher.png",
            "label": "tu"
          },
          {
            "src": "assets/img/classroom.png",
            "label": "vous",
            "is_correct": "true"
          },
          {
            "src": "assets/img/student.png",
            "label": "il"
          },
          {
            "src": "assets/img/desk.png",
            "label": "nous"
          }
        ],
        "hint": "Professors get the formal form, even if they're young.",
        "distractors": [
          "tu",
          "il",
          "nous"
        ],
        "direction": "target_to_source"
      }
    },
    {
      "id": "ex-tile-je-suis",
      "type": "exercise",
      "title": "Build: I am French",
      "exercise": {
        "id": "ex-tile-je-suis",
        "type": "word_tiles",
        "prompt": "Arrange the tiles to mean *I am French* (using masculine form).",
        "card_ids": [
          "etre-suis"
        ],
        "tiles": [
          "Je",
          "suis",
          "français"
        ],
        "hint": "Subject + être + adjective. Same order as English.",
        "direction": "target_to_source"
      }
    },
    {
      "id": "ex-tile-jai-faim",
      "type": "exercise",
      "title": "Build: I am hungry",
      "exercise": {
        "id": "ex-tile-jai-faim",
        "type": "word_tiles",
        "prompt": "Arrange the tiles to mean *I am hungry*. (Hint: French uses *avoir*, not *être*, for hunger.)",
        "card_ids": [
          "avoir-ai"
        ],
        "tiles": [
          "J'",
          "ai",
          "faim"
        ],
        "hint": "Literally *I have hunger* — French uses avoir for hunger / thirst / age.",
        "direction": "target_to_source"
      }
    },
    {
      "id": "ex-free-age",
      "type": "exercise",
      "title": "Saying your age",
      "exercise": {
        "id": "ex-free-age",
        "type": "free_text",
        "prompt": "Translate *I am 25 years old.* into French. (Hint: French uses *avoir* for age. Write out the number as a single word: *vingt-cinq*.)",
        "card_ids": [
          "avoir-ai"
        ],
        "accept": [
          "J'ai vingt-cinq ans.",
          "J'ai vingt-cinq ans",
          "j'ai vingt-cinq ans"
        ],
        "hint": "Start with *J'ai* (I have), then the number, then *ans* (years).",
        "distractors": [
          "Je suis vingt-cinq.",
          "Je suis vingt-cinq ans.",
          "J'ai vingt-cinq."
        ],
        "direction": "target_to_source"
      }
    },
    {
      "id": "ex-match-be-vs-have",
      "type": "exercise",
      "title": "Être or avoir?",
      "exercise": {
        "id": "ex-match-be-vs-have",
        "type": "matching",
        "prompt": "Match each English phrase to the French verb it uses.",
        "card_ids": [
          "etre-suis",
          "avoir-ai"
        ],
        "pairs": [
          {
            "left": "I am tall",
            "right": "être"
          },
          {
            "left": "I am hungry",
            "right": "avoir"
          },
          {
            "left": "I am 30",
            "right": "avoir"
          },
          {
            "left": "I am a student",
            "right": "être"
          }
        ],
        "direction": "target_to_source"
      }
    },
    {
      "id": "ex-cloze-avoir-amie",
      "type": "exercise",
      "title": "Cloze: avoir vs être (Phase 52H / v1.35.0)",
      "exercise": {
        "id": "ex-cloze-avoir-amie",
        "type": "cloze",
        "prompt": "Fill in the right form of *avoir* or *être*.",
        "card_ids": [
          "avoir-a"
        ],
        "sentence": "Elle ___ une amie.",
        "blanks": [
          {
            "accept": [
              "a"
            ],
            "hint": "*avoir* present, 3rd person singular",
            "placeholder": "?"
          }
        ],
        "cloze_mode": "type",
        "distractors": [
          "est",
          "as",
          "ont"
        ],
        "hint": "*Elle a une amie* = *She has a friend* — possession uses *avoir*. *Elle est une amie* would mean *She IS a friend* (identity, using *être*), which is grammatically valid but a different sentence."
      }
    }
  ]
}
